pymanifest/__init__.py
pymanifest/__main__.py
pymanifest-1.2.dist-info/LICENSE
pymanifest-1.2.dist-info/METADATA
pymanifest-1.2.dist-info/WHEEL
pymanifest-1.2.dist-info/top_level.txt
pymanifest-1.2.dist-info/RECORD
