Metadata-Version: 2.1
Name: pymanifest
Version: 1.2
Summary: File list utility
Home-page: https://github.com/claybrooks/pymanifest
Author: Clay Brooks
Author-email: clay_brooks@outlook.com
License: UNKNOWN
Platform: UNKNOWN
Classifier: Programming Language :: Python :: 3
Classifier: License :: OSI Approved :: The Unlicense (Unlicense)
Classifier: Operating System :: OS Independent
